ec2fleetd/__init__.py
ec2fleetd/__main__.py
ec2fleetd/aws.py
ec2fleetd/exceptions.py
ec2fleetd/magic.py
ec2fleetd-0.0.0.dist-info/METADATA
ec2fleetd-0.0.0.dist-info/WHEEL
ec2fleetd-0.0.0.dist-info/licenses/COPYING
ec2fleetd-0.0.0.dist-info/RECORD
