Metadata-Version: 2.1
Name: ec2fleetd
Version: 0.0.0
Summary: EC2 fleet init daemon
Project-URL: Homepage, https://github.com/si-magic/ec2fleetd
Project-URL: Issues, https://github.com/si-magic/ec2fleetd/issues
Author-email: David Timber <dxdt@dev.snart.me>
License-File: COPYING
Classifier: License :: OSI Approved :: GNU General Public License v3 (GPLv3)
Classifier: Operating System :: OS Independent
Classifier: Programming Language :: Python :: 3.12
Requires-Python: >=3.12
Requires-Dist: boto3
Requires-Dist: ec2imds
Requires-Dist: pyjson5
Requires-Dist: sdnotify
